LICENSE
MANIFEST.in
setup.py
lm_datahandler/__init__.py
lm_datahandler/datahandler.py
lm_datahandler.egg-info/PKG-INFO
lm_datahandler.egg-info/SOURCES.txt
lm_datahandler.egg-info/dependency_links.txt
lm_datahandler.egg-info/requires.txt
lm_datahandler.egg-info/top_level.txt
lm_datahandler/data_download/__init__.py
lm_datahandler/data_download/data_download.py
lm_datahandler/data_load/__init__.py
lm_datahandler/data_load/data_loader.py
lm_datahandler/data_load/loaders.py
lm_datahandler/function_in_test/__init__.py
lm_datahandler/function_in_test/other_features.py
lm_datahandler/function_in_test/realtime_sleep_analyse_test.py
lm_datahandler/functions/__init__.py
lm_datahandler/functions/biomarker.py
lm_datahandler/functions/feature_extract.py
lm_datahandler/functions/os_detect.py
lm_datahandler/functions/posture_analyse.py
lm_datahandler/functions/sleep_staging.py
lm_datahandler/functions/sleep_variable_compute.py
lm_datahandler/functions/spindle_detect.py
lm_datahandler/functions/wear_detect.py
lm_datahandler/models/realtime_sleep_staging.txt
lm_datahandler/models/wear_detection_1s.txt
lm_datahandler/models/wear_detection_1s_v1.txt
lm_datahandler/models/wear_detection_1s_v2.txt
lm_datahandler/models/wholenight_sleep_staging.txt
lm_datahandler/others/msyhbd.ttc
lm_datahandler/pdf/__init__.py
lm_datahandler/pdf/pdf_generator.py
lm_datahandler/plots/__init__.py
lm_datahandler/plots/cluster_plot.py
lm_datahandler/plots/metrics_plot.py
lm_datahandler/plots/rsp_contrast_plot.py
lm_datahandler/plots/sleep_staging_plot.py
lm_datahandler/plots/stim_plot.py
lm_datahandler/postprocess/__init__.py
lm_datahandler/postprocess/label_smooth.py
lm_datahandler/preprocess/__init__.py
lm_datahandler/preprocess/filter.py
lm_datahandler/preprocess/tailor.py
lm_datahandler/scripts/__init__.py
lm_datahandler/scripts/download_online_data.py
lm_datahandler/scripts/download_online_data_and_analyse.py
lm_datahandler/scripts/example.py
lm_datahandler/scripts/local_data_analyse.py
lm_datahandler/scripts/local_data_concat_and_analyse.py
lm_datahandler/scripts/script_functions.py
lm_datahandler/train/X8_online_sleep_analysis.py
lm_datahandler/train/__init__.py
