Metadata-Version: 2.1
Name: lm-datahandler
Version: 0.4.3
Summary: a python analyse tool for LM Data Recorder data
Home-page: https://github.com/zx950618/lm_datahandler
Author: Eric Zheng
Author-email: 1248471980@qq.com
License: MIT License
Keywords: eeg sleep staging analysis
Platform: any
License-File: LICENSE
